mkdocs_partial/__init__.py
mkdocs_partial/argparse_types.py
mkdocs_partial/docs_package_plugin.py
mkdocs_partial/entry_point.py
mkdocs_partial/mkdcos_helpers.py
mkdocs_partial/partial_docs_plugin.py
mkdocs_partial/site_entry_point.py
mkdocs_partial/version.py
mkdocs_partial/integrations/__init__.py
mkdocs_partial/integrations/macros_plugin_shim.py
mkdocs_partial/integrations/material_blog_integration.py
mkdocs_partial/integrations/redirect_plugin_shim.py
mkdocs_partial/integrations/spellcheck_plugin_shim.py
mkdocs_partial/packages/__init__.py
mkdocs_partial/packages/packager.py
mkdocs_partial/packages/templates/docs-package/dist-info/METADATA.j2
mkdocs_partial/packages/templates/docs-package/dist-info/WHEEL.j2
mkdocs_partial/packages/templates/docs-package/dist-info/entry_points.txt.j2
mkdocs_partial/packages/templates/docs-package/package/__init__.py.j2
mkdocs_partial/packages/templates/docs-package/package/plugin.py.j2
mkdocs_partial/packages/templates/docs-package/package/__pyinstaller/__init__.py.j2
mkdocs_partial/packages/templates/docs-package/package/__pyinstaller/hook-{{module_name}}.py.j2
mkdocs_partial/packages/templates/site-package/dist-info/METADATA.j2
mkdocs_partial/packages/templates/site-package/dist-info/WHEEL.j2
mkdocs_partial/packages/templates/site-package/dist-info/entry_points.txt.j2
mkdocs_partial/packages/templates/site-package/package/__init__.py.j2
mkdocs_partial/packages/templates/site-package/package/__main__.py.j2
mkdocs_partial/packages/templates/site-package/package/entry_point.py.j2
mkdocs_partial/packages/templates/site-package/package/__pyinstaller/__init__.py.j2
mkdocs_partial/packages/templates/site-package/package/__pyinstaller/hook-{{module_name}}.py.j2
mkdocs_partial/templating/__init__.py
mkdocs_partial/templating/markdown_extension.py
mkdocs_partial/templating/templater.py
mkdocs_partial/templating/templater_extension.py
mkdocs_partial/templating/version.py
mkdocs_partial-1.34.1.dist-info/licenses/LICENSE
mkdocs_partial-1.34.1.dist-info/METADATA
mkdocs_partial-1.34.1.dist-info/WHEEL
mkdocs_partial-1.34.1.dist-info/entry_points.txt
mkdocs_partial-1.34.1.dist-info/top_level.txt
mkdocs_partial-1.34.1.dist-info/RECORD
