Metadata-Version: 2.4
Name: mkdocs-partial
Version: 1.34.1
Summary: Mkdocs Partial Documentation
Author: Exorids
Author-email: public@exordis.com
Project-URL: Homepage, https://github.com/exordis/mkdocs-partial
Project-URL: Documentation, https://docs.exordis.com/documentation/partial-documentation/
Keywords: mkdocs,partial
Classifier: Programming Language :: Python :: 3
Classifier: License :: OSI Approved :: MIT License
Classifier: Operating System :: OS Independent
Requires-Python: >=3.12
License-File: LICENSE
Requires-Dist: setuptools<75,>=74
Requires-Dist: PyYAML<6.1,>=6.0.1
Requires-Dist: mkdocs<1.7,>=1.6
Requires-Dist: python-frontmatter<1.2,>=1.1.0
Requires-Dist: argparse<1.5,>=1.4
Requires-Dist: packaging>=24.0
Provides-Extra: lint
Requires-Dist: black<25,>=24.8; extra == "lint"
Requires-Dist: flake8<8.0.0,>=7.0.0; extra == "lint"
Requires-Dist: isort<6.0.0,>=5.13.0; extra == "lint"
Requires-Dist: pylint==3.3.0; extra == "lint"
Provides-Extra: test
Requires-Dist: pytest<8.0.0,>=7.1.3; extra == "test"
Requires-Dist: pytest-cov<4.0.0,>=3.0.0; extra == "test"
Requires-Dist: pytest-mock<4.0.0,>=3.0.0; extra == "test"
Requires-Dist: pytest-resource-path==1.3.0; extra == "test"
Requires-Dist: docs-documentation; extra == "test"
Dynamic: license-file
